AUTHORS.rst
CONTRIBUTING.rst
HISTORY.rst
LICENSE
MANIFEST.in
README.rst
setup.cfg
setup.py
docs/Makefile
docs/authors.rst
docs/conf.py
docs/contributing.rst
docs/history.rst
docs/index.rst
docs/installation.rst
docs/make.bat
docs/readme.rst
docs/usage.rst
tests/__init__.py
tests/tmlab_common/__init__.py
tests/tmlab_common/test_common.py
tests/tmlab_common/test_data/empty.csv
tests/tmlab_common/test_data/calc_pka/pKa.rad_PMF_last2ns3_1_good.txt
tests/tmlab_common/test_data/calc_pka/rad_PMF_last2ns3_1.txt
tmlab_common/__init__.py
tmlab_common/common.py
tmlab_common.egg-info/PKG-INFO
tmlab_common.egg-info/SOURCES.txt
tmlab_common.egg-info/dependency_links.txt
tmlab_common.egg-info/not-zip-safe
tmlab_common.egg-info/requires.txt
tmlab_common.egg-info/top_level.txt