Metadata-Version: 1.1
Name: tmlab-common
Version: 0.1.0
Summary: Common code used by Team Mayes and Blue Projects
Home-page: https://github.com/hmayes/tmlab_common
Author: Heather Mayes
Author-email: hbmayes@umich.edu
License: MIT license
Keywords: tmlab_common
Platform: UNKNOWN
Classifier: Development Status :: 2 - Pre-Alpha
Classifier: Intended Audience :: Developers
Classifier: License :: OSI Approved :: MIT License
Classifier: Natural Language :: English
Classifier: Programming Language :: Python :: 2
Classifier: Programming Language :: Python :: 2.6
Classifier: Programming Language :: Python :: 2.7
Classifier: Programming Language :: Python :: 3
Classifier: Programming Language :: Python :: 3.3
Classifier: Programming Language :: Python :: 3.4
Classifier: Programming Language :: Python :: 3.5
